SSIM_PIL/__init__.py
SSIM_PIL/__main__.py
SSIM_PIL/_cpu_strategy.py
SSIM_PIL/_gpu_strategy.py
SSIM_PIL/_gpu_strategy_new.py
SSIM_PIL/_numpy_strategy.py
SSIM_PIL-1.0.14.dist-info/LICENSE
SSIM_PIL-1.0.14.dist-info/METADATA
SSIM_PIL-1.0.14.dist-info/WHEEL
SSIM_PIL-1.0.14.dist-info/top_level.txt
SSIM_PIL-1.0.14.dist-info/RECORD
