Metadata-Version: 2.1
Name: SSIM-PIL
Version: 1.0.14
Summary: Comparison of two images using the structural similarity algorithm (SSIM).
Home-page: https://github.com/ChsHub/SSIM-PIL
Author: ChsHub
License: MIT License
Platform: UNKNOWN
Classifier: Programming Language :: Python :: 3
License-File: LICENSE
